pianocli/__init__.py
pianocli/main.py
pianocli/main.tcss
pianocli-1.1.0.dist-info/METADATA
pianocli-1.1.0.dist-info/WHEEL
pianocli-1.1.0.dist-info/entry_points.txt
pianocli-1.1.0.dist-info/top_level.txt
pianocli-1.1.0.dist-info/RECORD
