Metadata-Version: 2.4
Name: pianocli
Version: 1.1.0
Summary: A playable piano in your terminal.
Author-email: Manasvi <manasvi.bathula@gmail.com>
License: MIT
Classifier: Programming Language :: Python :: 3
Classifier: Operating System :: OS Independent
Requires-Python: >=3.8
Requires-Dist: textual
Requires-Dist: pyfluidsynth
Requires-Dist: typer
Requires-Dist: requests
Requires-Dist: appdirs
